[{"post_title":"NCT02090101"},{"post_title":"NCT02078375"},{"post_title":"NCT02100852"},{"post_title":"NCT02097654"},{"post_title":"NCT02085525"},{"post_title":"NCT02082093"},{"post_title":"NCT02078388"},{"post_title":"NCT02085538"},{"post_title":"NCT02097667"},{"post_title":"NCT02093442"},{"post_title":"NCT02100865"},{"post_title":"NCT02090114"},{"post_title":"NCT02078401"},{"post_title":"NCT02082106"},{"post_title":"NCT02093455"},{"post_title":"NCT02085551"},{"post_title":"NCT02097680"},{"post_title":"NCT02100878"},{"post_title":"NCT02090127"},{"post_title":"NCT02078414"},{"post_title":"NCT02082119"},{"post_title":"NCT02100891"},{"post_title":"NCT02090140"},{"post_title":"NCT02097693"},{"post_title":"NCT02085564"},{"post_title":"NCT02093468"},{"post_title":"NCT02078427"},{"post_title":"NCT02082132"},{"post_title":"NCT02085577"},{"post_title":"NCT02090153"},{"post_title":"NCT02097706"},{"post_title":"NCT02100904"},{"post_title":"NCT02093481"},{"post_title":"NCT02082145"},{"post_title":"NCT02085590"},{"post_title":"NCT02090166"},{"post_title":"NCT02093494"},{"post_title":"NCT02100917"},{"post_title":"NCT02074826"},{"post_title":"NCT02085603"},{"post_title":"NCT02078440"},{"post_title":"NCT02090179"},{"post_title":"NCT02082158"},{"post_title":"NCT02093507"},{"post_title":"NCT02100930"},{"post_title":"NCT02085616"},{"post_title":"NCT02074839"},{"post_title":"NCT02090192"},{"post_title":"NCT02082171"},{"post_title":"NCT02078453"},{"post_title":"NCT02100943"},{"post_title":"NCT02085629"},{"post_title":"NCT02093520"},{"post_title":"NCT02090205"},{"post_title":"NCT02078466"},{"post_title":"NCT02100956"},{"post_title":"NCT02085642"},{"post_title":"NCT02082184"},{"post_title":"NCT02078479"},{"post_title":"NCT02074852"},{"post_title":"NCT02090218"},{"post_title":"NCT02093533"},{"post_title":"NCT02085655"},{"post_title":"NCT02078492"},{"post_title":"NCT02074865"},{"post_title":"NCT02090231"},{"post_title":"NCT02082197"},{"post_title":"NCT02093546"},{"post_title":"NCT02078505"},{"post_title":"NCT02085668"},{"post_title":"NCT02074878"},{"post_title":"NCT02090244"},{"post_title":"NCT02093559"},{"post_title":"NCT02078518"},{"post_title":"NCT02090257"},{"post_title":"NCT02085681"},{"post_title":"NCT02074891"},{"post_title":"NCT02093572"},{"post_title":"NCT02078531"},{"post_title":"NCT02090270"},{"post_title":"NCT02085694"},{"post_title":"NCT02082210"},{"post_title":"NCT02078544"},{"post_title":"NCT02093585"},{"post_title":"NCT02074904"},{"post_title":"NCT02090283"},{"post_title":"NCT02085707"},{"post_title":"NCT02078557"},{"post_title":"NCT02093598"},{"post_title":"NCT02082223"},{"post_title":"NCT02074917"},{"post_title":"NCT02078570"},{"post_title":"NCT02090296"},{"post_title":"NCT02093611"},{"post_title":"NCT02082236"},{"post_title":"NCT02085720"},{"post_title":"NCT02074930"},{"post_title":"NCT02090309"},{"post_title":"NCT02085733"},{"post_title":"NCT02082249"},{"post_title":"NCT02093637"},{"post_title":"NCT02078583"},{"post_title":"NCT02090322"},{"post_title":"NCT02074943"},{"post_title":"NCT02085746"},{"post_title":"NCT02078596"},{"post_title":"NCT02093650"},{"post_title":"NCT02082262"},{"post_title":"NCT02090335"},{"post_title":"NCT02074956"},{"post_title":"NCT02085759"},{"post_title":"NCT02093663"},{"post_title":"NCT02078609"},{"post_title":"NCT02082275"},{"post_title":"NCT02085772"},{"post_title":"NCT02090348"},{"post_title":"NCT02074969"},{"post_title":"NCT02085785"},{"post_title":"NCT02082288"},{"post_title":"NCT02090361"},{"post_title":"NCT02078622"},{"post_title":"NCT02085798"},{"post_title":"NCT02093676"},{"post_title":"NCT02090374"},{"post_title":"NCT02082301"},{"post_title":"NCT02078635"},{"post_title":"NCT02093689"},{"post_title":"NCT02074982"},{"post_title":"NCT02090387"},{"post_title":"NCT02082314"},{"post_title":"NCT02085811"},{"post_title":"NCT02078648"},{"post_title":"NCT02090400"},{"post_title":"NCT02085824"},{"post_title":"NCT02093702"},{"post_title":"NCT02082327"},{"post_title":"NCT02085837"},{"post_title":"NCT02093715"},{"post_title":"NCT02082340"},{"post_title":"NCT02078661"},{"post_title":"NCT02085850"},{"post_title":"NCT02093728"},{"post_title":"NCT02082353"},{"post_title":"NCT02085863"},{"post_title":"NCT02078674"},{"post_title":"NCT02093741"},{"post_title":"NCT02085876"},{"post_title":"NCT02090413"},{"post_title":"NCT02074995"},{"post_title":"NCT02093754"}]