[{"post_title":"NCT02068235"},{"post_title":"NCT02053220"},{"post_title":"NCT02045927"},{"post_title":"NCT02049489"},{"post_title":"NCT02060370"},{"post_title":"NCT02042833"},{"post_title":"NCT02057016"},{"post_title":"NCT02053233"},{"post_title":"NCT02068248"},{"post_title":"NCT02045940"},{"post_title":"NCT02049502"},{"post_title":"NCT02057029"},{"post_title":"NCT02060383"},{"post_title":"NCT02053246"},{"post_title":"NCT02068261"},{"post_title":"NCT02045953"},{"post_title":"NCT02057042"},{"post_title":"NCT02049515"},{"post_title":"NCT02042846"},{"post_title":"NCT02045966"},{"post_title":"NCT02053259"},{"post_title":"NCT02068274"},{"post_title":"NCT02042859"},{"post_title":"NCT02057055"},{"post_title":"NCT02060396"},{"post_title":"NCT02053272"},{"post_title":"NCT02068287"},{"post_title":"NCT02042872"},{"post_title":"NCT02057068"},{"post_title":"NCT02045979"},{"post_title":"NCT02060409"},{"post_title":"NCT02045992"},{"post_title":"NCT02049528"},{"post_title":"NCT02042885"},{"post_title":"NCT02053285"},{"post_title":"NCT02057081"},{"post_title":"NCT02049541"},{"post_title":"NCT02060422"},{"post_title":"NCT02046005"},{"post_title":"NCT02042898"},{"post_title":"NCT02053298"},{"post_title":"NCT02057094"},{"post_title":"NCT02049554"},{"post_title":"NCT02060435"},{"post_title":"NCT02053311"},{"post_title":"NCT02046018"},{"post_title":"NCT02049567"},{"post_title":"NCT02060448"},{"post_title":"NCT02057107"},{"post_title":"NCT02046031"},{"post_title":"NCT02053324"},{"post_title":"NCT02049580"},{"post_title":"NCT02057120"},{"post_title":"NCT02060461"},{"post_title":"NCT02046044"},{"post_title":"NCT02049593"},{"post_title":"NCT02042911"},{"post_title":"NCT02053337"},{"post_title":"NCT02057133"},{"post_title":"NCT02046057"},{"post_title":"NCT02060474"},{"post_title":"NCT02049606"},{"post_title":"NCT02053350"},{"post_title":"NCT02042924"},{"post_title":"NCT02046070"},{"post_title":"NCT02049619"},{"post_title":"NCT02060487"},{"post_title":"NCT02042937"},{"post_title":"NCT02053363"},{"post_title":"NCT02057146"},{"post_title":"NCT02049632"},{"post_title":"NCT02042950"},{"post_title":"NCT02046083"},{"post_title":"NCT02057159"},{"post_title":"NCT02049645"},{"post_title":"NCT02042963"},{"post_title":"NCT02046096"},{"post_title":"NCT02053376"},{"post_title":"NCT02057172"},{"post_title":"NCT02049658"},{"post_title":"NCT02060500"},{"post_title":"NCT02042976"},{"post_title":"NCT02053389"},{"post_title":"NCT02049671"},{"post_title":"NCT02057185"},{"post_title":"NCT02060513"},{"post_title":"NCT02046109"},{"post_title":"NCT02049684"},{"post_title":"NCT02053402"},{"post_title":"NCT02042989"},{"post_title":"NCT02057198"},{"post_title":"NCT02049697"},{"post_title":"NCT02046122"},{"post_title":"NCT02053415"},{"post_title":"NCT02043002"},{"post_title":"NCT02049710"},{"post_title":"NCT02057211"},{"post_title":"NCT02046135"},{"post_title":"NCT02053428"},{"post_title":"NCT02057224"},{"post_title":"NCT02049723"},{"post_title":"NCT02043015"},{"post_title":"NCT02060526"},{"post_title":"NCT02049736"},{"post_title":"NCT02043028"},{"post_title":"NCT02057237"},{"post_title":"NCT02053441"},{"post_title":"NCT02043041"},{"post_title":"NCT02046148"},{"post_title":"NCT02053454"},{"post_title":"NCT02049749"},{"post_title":"NCT02043054"},{"post_title":"NCT02060539"},{"post_title":"NCT02046161"},{"post_title":"NCT02049762"},{"post_title":"NCT02053467"},{"post_title":"NCT02057250"},{"post_title":"NCT02043067"},{"post_title":"NCT02046174"},{"post_title":"NCT02060552"},{"post_title":"NCT02049775"},{"post_title":"NCT02043080"},{"post_title":"NCT02046187"},{"post_title":"NCT02053480"},{"post_title":"NCT02060565"},{"post_title":"NCT02049788"},{"post_title":"NCT02043093"},{"post_title":"NCT02049801"},{"post_title":"NCT02060578"},{"post_title":"NCT02057263"},{"post_title":"NCT02043106"},{"post_title":"NCT02060591"},{"post_title":"NCT02049814"},{"post_title":"NCT02057276"},{"post_title":"NCT02046200"},{"post_title":"NCT02043119"},{"post_title":"NCT02060604"},{"post_title":"NCT02053493"},{"post_title":"NCT02049827"},{"post_title":"NCT02057289"},{"post_title":"NCT02046213"},{"post_title":"NCT02060617"},{"post_title":"NCT02043132"},{"post_title":"NCT02049840"},{"post_title":"NCT02057302"},{"post_title":"NCT02046226"},{"post_title":"NCT02060630"},{"post_title":"NCT02049853"},{"post_title":"NCT02057315"},{"post_title":"NCT02053506"}]