[{"post_title":"NCT04935086"},{"post_title":"NCT04931238"},{"post_title":"NCT04935099"},{"post_title":"NCT04927793"},{"post_title":"NCT04931251"},{"post_title":"NCT04927806"},{"post_title":"NCT04935112"},{"post_title":"NCT04927819"},{"post_title":"NCT04935125"},{"post_title":"NCT04931264"},{"post_title":"NCT04927832"},{"post_title":"NCT04935138"},{"post_title":"NCT04931277"},{"post_title":"NCT04927845"},{"post_title":"NCT04935151"},{"post_title":"NCT04931290"},{"post_title":"NCT04927858"},{"post_title":"NCT04935164"},{"post_title":"NCT04931303"},{"post_title":"NCT04927871"},{"post_title":"NCT04935177"},{"post_title":"NCT04935190"},{"post_title":"NCT04927884"},{"post_title":"NCT04931316"},{"post_title":"NCT04935203"},{"post_title":"NCT04927897"},{"post_title":"NCT04931329"},{"post_title":"NCT04935216"},{"post_title":"NCT04927910"},{"post_title":"NCT04931342"},{"post_title":"NCT04935229"},{"post_title":"NCT04927923"},{"post_title":"NCT04935242"},{"post_title":"NCT04935255"},{"post_title":"NCT04927936"},{"post_title":"NCT04935268"},{"post_title":"NCT04927949"},{"post_title":"NCT04931355"},{"post_title":"NCT04935281"},{"post_title":"NCT04931368"},{"post_title":"NCT04927962"},{"post_title":"NCT04935294"},{"post_title":"NCT04931381"},{"post_title":"NCT04927975"},{"post_title":"NCT04935307"},{"post_title":"NCT04931394"},{"post_title":"NCT04935320"},{"post_title":"NCT04931407"},{"post_title":"NCT04935333"},{"post_title":"NCT04927988"},{"post_title":"NCT04931420"},{"post_title":"NCT04935346"},{"post_title":"NCT04928001"},{"post_title":"NCT04931433"},{"post_title":"NCT04935359"},{"post_title":"NCT04928014"},{"post_title":"NCT04935372"},{"post_title":"NCT04931446"},{"post_title":"NCT04928027"},{"post_title":"NCT04935385"},{"post_title":"NCT04931459"},{"post_title":"NCT04928040"},{"post_title":"NCT04935398"},{"post_title":"NCT04935411"},{"post_title":"NCT04931472"},{"post_title":"NCT04928053"},{"post_title":"NCT04931485"},{"post_title":"NCT04935424"},{"post_title":"NCT04928066"},{"post_title":"NCT04935437"},{"post_title":"NCT04931498"},{"post_title":"NCT04928079"},{"post_title":"NCT04931511"},{"post_title":"NCT04935450"},{"post_title":"NCT04928092"},{"post_title":"NCT04931524"},{"post_title":"NCT04935463"},{"post_title":"NCT04928105"},{"post_title":"NCT04931537"},{"post_title":"NCT04928118"},{"post_title":"NCT04935476"},{"post_title":"NCT04931550"},{"post_title":"NCT04928131"},{"post_title":"NCT04928144"},{"post_title":"NCT04931563"},{"post_title":"NCT04935489"},{"post_title":"NCT04928157"},{"post_title":"NCT04935502"},{"post_title":"NCT04931576"},{"post_title":"NCT04935515"},{"post_title":"NCT04928170"},{"post_title":"NCT04931589"},{"post_title":"NCT04935528"},{"post_title":"NCT04928183"},{"post_title":"NCT04931602"},{"post_title":"NCT04935541"},{"post_title":"NCT04928196"},{"post_title":"NCT04931615"},{"post_title":"NCT04928209"},{"post_title":"NCT04935554"},{"post_title":"NCT04931628"},{"post_title":"NCT04935567"},{"post_title":"NCT04928222"},{"post_title":"NCT04931641"},{"post_title":"NCT04935580"},{"post_title":"NCT04928235"},{"post_title":"NCT04931654"},{"post_title":"NCT04935593"},{"post_title":"NCT04928248"},{"post_title":"NCT04931667"},{"post_title":"NCT04935606"},{"post_title":"NCT04928261"},{"post_title":"NCT04935619"},{"post_title":"NCT04928274"},{"post_title":"NCT04931680"},{"post_title":"NCT04928287"},{"post_title":"NCT04935632"},{"post_title":"NCT04931693"},{"post_title":"NCT04935645"},{"post_title":"NCT04928300"},{"post_title":"NCT04931706"},{"post_title":"NCT04935658"},{"post_title":"NCT04928313"},{"post_title":"NCT04931719"},{"post_title":"NCT04935671"},{"post_title":"NCT04928326"},{"post_title":"NCT04931732"},{"post_title":"NCT04935684"},{"post_title":"NCT04928339"},{"post_title":"NCT04931745"},{"post_title":"NCT04928352"},{"post_title":"NCT04935697"},{"post_title":"NCT04931758"},{"post_title":"NCT04928365"},{"post_title":"NCT04931771"},{"post_title":"NCT04935710"},{"post_title":"NCT04928378"},{"post_title":"NCT04928391"},{"post_title":"NCT04931784"},{"post_title":"NCT04935723"},{"post_title":"NCT04928404"},{"post_title":"NCT04931797"},{"post_title":"NCT04935736"},{"post_title":"NCT04928417"},{"post_title":"NCT04931810"},{"post_title":"NCT04928430"},{"post_title":"NCT04935749"},{"post_title":"NCT04931823"},{"post_title":"NCT04928443"},{"post_title":"NCT04935762"}]