[{"post_title":"NCT04996134"},{"post_title":"NCT04989673"},{"post_title":"NCT04999410"},{"post_title":"NCT04996147"},{"post_title":"NCT04992949"},{"post_title":"NCT04996160"},{"post_title":"NCT04999423"},{"post_title":"NCT04989686"},{"post_title":"NCT04999436"},{"post_title":"NCT04992962"},{"post_title":"NCT04996173"},{"post_title":"NCT04989699"},{"post_title":"NCT04999449"},{"post_title":"NCT04992975"},{"post_title":"NCT04996186"},{"post_title":"NCT04989712"},{"post_title":"NCT04999462"},{"post_title":"NCT04992988"},{"post_title":"NCT04989725"},{"post_title":"NCT04996199"},{"post_title":"NCT04999475"},{"post_title":"NCT04993001"},{"post_title":"NCT04996212"},{"post_title":"NCT04989738"},{"post_title":"NCT04999488"},{"post_title":"NCT04993014"},{"post_title":"NCT04989751"},{"post_title":"NCT04996225"},{"post_title":"NCT04989764"},{"post_title":"NCT04993027"},{"post_title":"NCT04996238"},{"post_title":"NCT04989777"},{"post_title":"NCT04993040"},{"post_title":"NCT04996251"},{"post_title":"NCT04993053"},{"post_title":"NCT04989790"},{"post_title":"NCT04996264"},{"post_title":"NCT04993066"},{"post_title":"NCT04993079"},{"post_title":"NCT04989803"},{"post_title":"NCT04996277"},{"post_title":"NCT04989816"},{"post_title":"NCT04993092"},{"post_title":"NCT04996290"},{"post_title":"NCT04993105"},{"post_title":"NCT04996303"},{"post_title":"NCT04989829"},{"post_title":"NCT04993118"},{"post_title":"NCT04989842"},{"post_title":"NCT04996316"},{"post_title":"NCT04993131"},{"post_title":"NCT04996329"},{"post_title":"NCT04989855"},{"post_title":"NCT04993144"},{"post_title":"NCT04989868"},{"post_title":"NCT04993157"},{"post_title":"NCT04996342"},{"post_title":"NCT04989881"},{"post_title":"NCT04993170"},{"post_title":"NCT04996355"},{"post_title":"NCT04989894"},{"post_title":"NCT04996368"},{"post_title":"NCT04993183"},{"post_title":"NCT04989907"},{"post_title":"NCT04996381"},{"post_title":"NCT04993196"},{"post_title":"NCT04989920"},{"post_title":"NCT04996394"},{"post_title":"NCT04993209"},{"post_title":"NCT04989933"},{"post_title":"NCT04996407"},{"post_title":"NCT04993222"},{"post_title":"NCT04989946"},{"post_title":"NCT04996420"},{"post_title":"NCT04993235"},{"post_title":"NCT04989959"},{"post_title":"NCT04996433"},{"post_title":"NCT04993248"},{"post_title":"NCT04989972"},{"post_title":"NCT04993261"},{"post_title":"NCT04996446"},{"post_title":"NCT04989985"},{"post_title":"NCT04993274"},{"post_title":"NCT04996459"},{"post_title":"NCT04993287"},{"post_title":"NCT04989998"},{"post_title":"NCT04996472"},{"post_title":"NCT04990011"},{"post_title":"NCT04993300"},{"post_title":"NCT04990024"},{"post_title":"NCT04993313"},{"post_title":"NCT04996485"},{"post_title":"NCT04993326"},{"post_title":"NCT04990037"},{"post_title":"NCT04996498"},{"post_title":"NCT04993339"},{"post_title":"NCT04990050"},{"post_title":"NCT04996511"},{"post_title":"NCT04990063"},{"post_title":"NCT04993352"},{"post_title":"NCT04996524"},{"post_title":"NCT04993365"},{"post_title":"NCT04990076"},{"post_title":"NCT04996537"},{"post_title":"NCT04993378"},{"post_title":"NCT04990089"},{"post_title":"NCT04996550"},{"post_title":"NCT04993391"},{"post_title":"NCT04990102"},{"post_title":"NCT04996563"},{"post_title":"NCT04990115"},{"post_title":"NCT04993404"},{"post_title":"NCT04996576"},{"post_title":"NCT04990128"},{"post_title":"NCT04993417"},{"post_title":"NCT04996589"},{"post_title":"NCT04990141"},{"post_title":"NCT04996602"},{"post_title":"NCT04993430"},{"post_title":"NCT04996615"},{"post_title":"NCT04990154"},{"post_title":"NCT04993443"},{"post_title":"NCT04996628"},{"post_title":"NCT04990167"},{"post_title":"NCT04993456"},{"post_title":"NCT04996641"},{"post_title":"NCT04990180"},{"post_title":"NCT04993469"},{"post_title":"NCT04996654"},{"post_title":"NCT04990193"},{"post_title":"NCT04993482"},{"post_title":"NCT04990206"},{"post_title":"NCT04996667"},{"post_title":"NCT04993495"},{"post_title":"NCT04990219"},{"post_title":"NCT04996680"},{"post_title":"NCT04990232"},{"post_title":"NCT04996693"},{"post_title":"NCT04993508"},{"post_title":"NCT04996706"},{"post_title":"NCT04990245"},{"post_title":"NCT04993521"},{"post_title":"NCT04990258"},{"post_title":"NCT04996719"},{"post_title":"NCT04990271"},{"post_title":"NCT04993534"},{"post_title":"NCT04996732"},{"post_title":"NCT04993547"},{"post_title":"NCT04990284"},{"post_title":"NCT04996745"}]