[{"post_title":"NCT03639597"},{"post_title":"NCT03649633"},{"post_title":"NCT03653299"},{"post_title":"NCT03660891"},{"post_title":"NCT03646227"},{"post_title":"NCT03639610"},{"post_title":"NCT03642938"},{"post_title":"NCT03656757"},{"post_title":"NCT03660904"},{"post_title":"NCT03653312"},{"post_title":"NCT03649646"},{"post_title":"NCT03656770"},{"post_title":"NCT03646240"},{"post_title":"NCT03660917"},{"post_title":"NCT03642951"},{"post_title":"NCT03649659"},{"post_title":"NCT03639623"},{"post_title":"NCT03653325"},{"post_title":"NCT03656783"},{"post_title":"NCT03636204"},{"post_title":"NCT03646253"},{"post_title":"NCT03660930"},{"post_title":"NCT03642964"},{"post_title":"NCT03653338"},{"post_title":"NCT03639636"},{"post_title":"NCT03649672"},{"post_title":"NCT03646266"},{"post_title":"NCT03656796"},{"post_title":"NCT03660943"},{"post_title":"NCT03642977"},{"post_title":"NCT03636217"},{"post_title":"NCT03646279"},{"post_title":"NCT03653351"},{"post_title":"NCT03656809"},{"post_title":"NCT03639649"},{"post_title":"NCT03649685"},{"post_title":"NCT03642990"},{"post_title":"NCT03636230"},{"post_title":"NCT03646292"},{"post_title":"NCT03653364"},{"post_title":"NCT03639662"},{"post_title":"NCT03656822"},{"post_title":"NCT03649698"},{"post_title":"NCT03646305"},{"post_title":"NCT03636243"},{"post_title":"NCT03660956"},{"post_title":"NCT03643003"},{"post_title":"NCT03656835"},{"post_title":"NCT03639675"},{"post_title":"NCT03646318"},{"post_title":"NCT03649711"},{"post_title":"NCT03660969"},{"post_title":"NCT03643016"},{"post_title":"NCT03653377"},{"post_title":"NCT03636256"},{"post_title":"NCT03646331"},{"post_title":"NCT03656848"},{"post_title":"NCT03639688"},{"post_title":"NCT03646344"},{"post_title":"NCT03643029"},{"post_title":"NCT03649724"},{"post_title":"NCT03660982"},{"post_title":"NCT03653390"},{"post_title":"NCT03656861"},{"post_title":"NCT03639701"},{"post_title":"NCT03636269"},{"post_title":"NCT03646357"},{"post_title":"NCT03643042"},{"post_title":"NCT03649737"},{"post_title":"NCT03653403"},{"post_title":"NCT03660995"},{"post_title":"NCT03656874"},{"post_title":"NCT03639714"},{"post_title":"NCT03643055"},{"post_title":"NCT03653416"},{"post_title":"NCT03661008"},{"post_title":"NCT03656887"},{"post_title":"NCT03646370"},{"post_title":"NCT03649750"},{"post_title":"NCT03643068"},{"post_title":"NCT03653429"},{"post_title":"NCT03661021"},{"post_title":"NCT03639727"},{"post_title":"NCT03656900"},{"post_title":"NCT03636282"},{"post_title":"NCT03649763"},{"post_title":"NCT03646383"},{"post_title":"NCT03653442"},{"post_title":"NCT03643081"},{"post_title":"NCT03639740"},{"post_title":"NCT03661034"},{"post_title":"NCT03646396"},{"post_title":"NCT03656913"},{"post_title":"NCT03649776"},{"post_title":"NCT03653455"},{"post_title":"NCT03636295"},{"post_title":"NCT03643094"},{"post_title":"NCT03646409"},{"post_title":"NCT03649789"},{"post_title":"NCT03656926"},{"post_title":"NCT03639753"},{"post_title":"NCT03661047"},{"post_title":"NCT03653468"},{"post_title":"NCT03636308"},{"post_title":"NCT03643107"},{"post_title":"NCT03646422"},{"post_title":"NCT03639766"},{"post_title":"NCT03649802"},{"post_title":"NCT03653481"},{"post_title":"NCT03636321"},{"post_title":"NCT03661060"},{"post_title":"NCT03643120"},{"post_title":"NCT03639779"},{"post_title":"NCT03649815"},{"post_title":"NCT03646435"},{"post_title":"NCT03653494"},{"post_title":"NCT03636334"},{"post_title":"NCT03656939"},{"post_title":"NCT03646448"},{"post_title":"NCT03649828"},{"post_title":"NCT03643133"},{"post_title":"NCT03639792"},{"post_title":"NCT03653507"},{"post_title":"NCT03646461"},{"post_title":"NCT03636347"},{"post_title":"NCT03656952"},{"post_title":"NCT03639805"},{"post_title":"NCT03649841"},{"post_title":"NCT03661073"},{"post_title":"NCT03643146"},{"post_title":"NCT03656965"},{"post_title":"NCT03646474"},{"post_title":"NCT03639818"},{"post_title":"NCT03661086"},{"post_title":"NCT03649854"},{"post_title":"NCT03643159"},{"post_title":"NCT03656978"},{"post_title":"NCT03646487"},{"post_title":"NCT03636360"},{"post_title":"NCT03653520"},{"post_title":"NCT03649867"},{"post_title":"NCT03639831"},{"post_title":"NCT03661099"},{"post_title":"NCT03643172"},{"post_title":"NCT03656991"},{"post_title":"NCT03636373"},{"post_title":"NCT03646500"},{"post_title":"NCT03653533"},{"post_title":"NCT03649880"},{"post_title":"NCT03661112"}]