[{"post_title":"NCT01176240"},{"post_title":"NCT01183377"},{"post_title":"NCT01168544"},{"post_title":"NCT01164865"},{"post_title":"NCT01172639"},{"post_title":"NCT01179529"},{"post_title":"NCT01183390"},{"post_title":"NCT01168557"},{"post_title":"NCT01161628"},{"post_title":"NCT01164878"},{"post_title":"NCT01179542"},{"post_title":"NCT01183403"},{"post_title":"NCT01172652"},{"post_title":"NCT01168570"},{"post_title":"NCT01161641"},{"post_title":"NCT01179555"},{"post_title":"NCT01168583"},{"post_title":"NCT01164891"},{"post_title":"NCT01183416"},{"post_title":"NCT01172665"},{"post_title":"NCT01161654"},{"post_title":"NCT01176253"},{"post_title":"NCT01183429"},{"post_title":"NCT01164904"},{"post_title":"NCT01172691"},{"post_title":"NCT01179568"},{"post_title":"NCT01161667"},{"post_title":"NCT01183442"},{"post_title":"NCT01172704"},{"post_title":"NCT01168596"},{"post_title":"NCT01176266"},{"post_title":"NCT01161680"},{"post_title":"NCT01164917"},{"post_title":"NCT01183455"},{"post_title":"NCT01179581"},{"post_title":"NCT01172717"},{"post_title":"NCT01168609"},{"post_title":"NCT01161693"},{"post_title":"NCT01179594"},{"post_title":"NCT01164930"},{"post_title":"NCT01172730"},{"post_title":"NCT01168622"},{"post_title":"NCT01176279"},{"post_title":"NCT01161706"},{"post_title":"NCT01179607"},{"post_title":"NCT01183468"},{"post_title":"NCT01172743"},{"post_title":"NCT01164943"},{"post_title":"NCT01168635"},{"post_title":"NCT01161719"},{"post_title":"NCT01179620"},{"post_title":"NCT01176292"},{"post_title":"NCT01172756"},{"post_title":"NCT01164956"},{"post_title":"NCT01168648"},{"post_title":"NCT01176305"},{"post_title":"NCT01179633"},{"post_title":"NCT01161732"},{"post_title":"NCT01183481"},{"post_title":"NCT01172769"},{"post_title":"NCT01164969"},{"post_title":"NCT01176318"},{"post_title":"NCT01168661"},{"post_title":"NCT01179646"},{"post_title":"NCT01161745"},{"post_title":"NCT01183494"},{"post_title":"NCT01172782"},{"post_title":"NCT01164982"},{"post_title":"NCT01176331"},{"post_title":"NCT01161758"},{"post_title":"NCT01179659"},{"post_title":"NCT01172795"},{"post_title":"NCT01168674"},{"post_title":"NCT01164995"},{"post_title":"NCT01176344"},{"post_title":"NCT01183507"},{"post_title":"NCT01168687"},{"post_title":"NCT01165008"},{"post_title":"NCT01176357"},{"post_title":"NCT01161771"},{"post_title":"NCT01183520"},{"post_title":"NCT01168700"},{"post_title":"NCT01161784"},{"post_title":"NCT01176370"},{"post_title":"NCT01165021"},{"post_title":"NCT01183533"},{"post_title":"NCT01172808"},{"post_title":"NCT01168713"},{"post_title":"NCT01176383"},{"post_title":"NCT01179672"},{"post_title":"NCT01161797"},{"post_title":"NCT01165034"},{"post_title":"NCT01183546"},{"post_title":"NCT01176396"},{"post_title":"NCT01161810"},{"post_title":"NCT01165047"},{"post_title":"NCT01183559"},{"post_title":"NCT01179685"},{"post_title":"NCT01176409"},{"post_title":"NCT01165060"},{"post_title":"NCT01183572"},{"post_title":"NCT01179698"},{"post_title":"NCT01161823"},{"post_title":"NCT01168726"},{"post_title":"NCT01183585"},{"post_title":"NCT01176422"},{"post_title":"NCT01165073"},{"post_title":"NCT01179711"},{"post_title":"NCT01161836"},{"post_title":"NCT01172821"},{"post_title":"NCT01183598"},{"post_title":"NCT01168739"},{"post_title":"NCT01176435"},{"post_title":"NCT01165086"},{"post_title":"NCT01179724"},{"post_title":"NCT01161849"},{"post_title":"NCT01183611"},{"post_title":"NCT01165099"},{"post_title":"NCT01168752"},{"post_title":"NCT01176448"},{"post_title":"NCT01161862"},{"post_title":"NCT01157910"},{"post_title":"NCT01183624"},{"post_title":"NCT01168765"},{"post_title":"NCT01161875"},{"post_title":"NCT01165112"},{"post_title":"NCT01176461"},{"post_title":"NCT01157923"},{"post_title":"NCT01172834"},{"post_title":"NCT01161888"},{"post_title":"NCT01183637"},{"post_title":"NCT01168778"},{"post_title":"NCT01165125"},{"post_title":"NCT01157936"},{"post_title":"NCT01176474"},{"post_title":"NCT01172847"},{"post_title":"NCT01179737"},{"post_title":"NCT01161901"},{"post_title":"NCT01168791"},{"post_title":"NCT01183650"},{"post_title":"NCT01157949"},{"post_title":"NCT01176487"},{"post_title":"NCT01172860"},{"post_title":"NCT01161914"},{"post_title":"NCT01179750"},{"post_title":"NCT01183663"},{"post_title":"NCT01157962"},{"post_title":"NCT01179763"},{"post_title":"NCT01161927"},{"post_title":"NCT01176500"}]